setup.py
tmuxpair.py
tmuxpair.egg-info/PKG-INFO
tmuxpair.egg-info/SOURCES.txt
tmuxpair.egg-info/dependency_links.txt
tmuxpair.egg-info/entry_points.txt
tmuxpair.egg-info/requires.txt
tmuxpair.egg-info/top_level.txt