Metadata-Version: 1.1
Name: tmuxpair
Version: 1.0.0
Summary: Command line script for setting up a temporary tmux session for pair programming
Home-page: https://github.com/goerz/tmuxpair#tmuxpair
Author: Michael Goerz
Author-email: goerz@stanford.edu
License: UNKNOWN
Platform: UNKNOWN
Classifier: Environment :: Console
Classifier: Natural Language :: English
Classifier: License :: OSI Approved :: MIT License
Classifier: Programming Language :: Python
Classifier: Programming Language :: Python :: 2
Classifier: Programming Language :: Python :: 2.7
Classifier: Programming Language :: Python :: 3
Classifier: Programming Language :: Python :: 3.3
Classifier: Programming Language :: Python :: 3.4
Classifier: Programming Language :: Python :: 3.5
